{
	"info": {
		"_postman_id": "950c6a82-b22d-4728-9444-ac9cb442546e",
		"name": "Auth",
		"schema": "https://schema.getpostman.com/json/collection/v2.1.0/collection.json"
	},
	"item": [
		{
			"name": "Login",
			"request": {
				"auth": {
					"type": "noauth"
				},
				"method": "POST",
				"header": [],
				"body": {
					"mode": "urlencoded",
					"urlencoded": [
						{
							"key": "user_name",
							"value": "abc",
							"type": "text"
						},
						{
							"key": "password",
							"value": "xyz",
							"type": "text"
						}
					]
				},
				"url": {
					"raw": "http://localhost:3000/api/v1/",
					"protocol": "http",
					"host": [
						"localhost"
					],
					"port": "3000",
					"path": [
						"api",
						"v1",
						""
					]
				}
			},
			"response": []
		},
		{
			"name": "Registration",
			"request": {
				"method": "POST",
				"header": [],
				"body": {
					"mode": "urlencoded",
					"urlencoded": [
						{
							"key": "user_name",
							"value": "xyz",
							"type": "text"
						},
						{
							"key": "password",
							"value": "abc",
							"type": "text"
						}
					]
				},
				"url": {
					"raw": "http://localhost:3000/api/v1/registration",
					"protocol": "http",
					"host": [
						"localhost"
					],
					"port": "3000",
					"path": [
						"api",
						"v1",
						"registration"
					]
				}
			},
			"response": []
		}
	]
}